odoo10_addon_account_invoice_merge_attachment-10.0.1.0.0-py2.7-nspkg.pth
odoo/addons/account_invoice_merge_attachment/README.rst
odoo/addons/account_invoice_merge_attachment/__init__.py
odoo/addons/account_invoice_merge_attachment/__manifest__.py
odoo/addons/account_invoice_merge_attachment/models/__init__.py
odoo/addons/account_invoice_merge_attachment/models/account_invoice.py
odoo/addons/account_invoice_merge_attachment/static/description/icon.png
odoo/addons/account_invoice_merge_attachment/tests/__init__.py
odoo/addons/account_invoice_merge_attachment/tests/test_account_invoice_merge_attachment.py
odoo/addons/account_invoice_merge_attachment/wizards/__init__.py
odoo/addons/account_invoice_merge_attachment/wizards/invoice_merge.py
odoo/addons/account_invoice_merge_attachment/wizards/invoice_merge.xml
odoo10_addon_account_invoice_merge_attachment-10.0.1.0.0.dist-info/DESCRIPTION.rst
odoo10_addon_account_invoice_merge_attachment-10.0.1.0.0.dist-info/METADATA
odoo10_addon_account_invoice_merge_attachment-10.0.1.0.0.dist-info/RECORD
odoo10_addon_account_invoice_merge_attachment-10.0.1.0.0.dist-info/WHEEL
odoo10_addon_account_invoice_merge_attachment-10.0.1.0.0.dist-info/metadata.json
odoo10_addon_account_invoice_merge_attachment-10.0.1.0.0.dist-info/namespace_packages.txt
odoo10_addon_account_invoice_merge_attachment-10.0.1.0.0.dist-info/top_level.txt
